torchgeo/__init__.py
torchgeo/__main__.py
torchgeo/main.py
torchgeo/py.typed
torchgeo/datamodules/__init__.py
torchgeo/datamodules/agrifieldnet.py
torchgeo/datamodules/bigearthnet.py
torchgeo/datamodules/bright.py
torchgeo/datamodules/cabuar.py
torchgeo/datamodules/caffe.py
torchgeo/datamodules/chabud.py
torchgeo/datamodules/chesapeake.py
torchgeo/datamodules/cowc.py
torchgeo/datamodules/cyclone.py
torchgeo/datamodules/deepglobelandcover.py
torchgeo/datamodules/digital_typhoon.py
torchgeo/datamodules/etci2021.py
torchgeo/datamodules/eurosat.py
torchgeo/datamodules/fair1m.py
torchgeo/datamodules/fire_risk.py
torchgeo/datamodules/ftw.py
torchgeo/datamodules/geo.py
torchgeo/datamodules/geonrw.py
torchgeo/datamodules/gid15.py
torchgeo/datamodules/hyspecnet.py
torchgeo/datamodules/inria.py
torchgeo/datamodules/iobench.py
torchgeo/datamodules/l7irish.py
torchgeo/datamodules/l8biome.py
torchgeo/datamodules/landcoverai.py
torchgeo/datamodules/levircd.py
torchgeo/datamodules/loveda.py
torchgeo/datamodules/mmflood.py
torchgeo/datamodules/naip.py
torchgeo/datamodules/nasa_marine_debris.py
torchgeo/datamodules/oscd.py
torchgeo/datamodules/pastis.py
torchgeo/datamodules/patternnet.py
torchgeo/datamodules/potsdam.py
torchgeo/datamodules/quakeset.py
torchgeo/datamodules/reforestree.py
torchgeo/datamodules/resisc45.py
torchgeo/datamodules/seco.py
torchgeo/datamodules/sen12ms.py
torchgeo/datamodules/sentinel2_cdl.py
torchgeo/datamodules/sentinel2_eurocrops.py
torchgeo/datamodules/sentinel2_nccm.py
torchgeo/datamodules/sentinel2_south_america_soybean.py
torchgeo/datamodules/skippd.py
torchgeo/datamodules/so2sat.py
torchgeo/datamodules/solar_plants_brazil.py
torchgeo/datamodules/southafricacroptype.py
torchgeo/datamodules/spacenet.py
torchgeo/datamodules/ssl4eo.py
torchgeo/datamodules/ssl4eo_benchmark.py
torchgeo/datamodules/substation.py
torchgeo/datamodules/sustainbench_crop_yield.py
torchgeo/datamodules/treesatai.py
torchgeo/datamodules/ucmerced.py
torchgeo/datamodules/usavars.py
torchgeo-0.8.1.dist-info/licenses/LICENSE
torchgeo-0.8.1.dist-info/METADATA
torchgeo-0.8.1.dist-info/WHEEL
torchgeo-0.8.1.dist-info/entry_points.txt
torchgeo-0.8.1.dist-info/top_level.txt
torchgeo-0.8.1.dist-info/RECORD
