Metadata-Version: 2.4
Name: torchgeo
Version: 0.8.1
Summary: TorchGeo: datasets, samplers, transforms, and pre-trained models for geospatial data
Author-email: "Adam J. Stewart" <ajstewart426@gmail.com>
Maintainer-email: "Adam J. Stewart" <ajstewart426@gmail.com>, Caleb Robinson <Caleb.Robinson@microsoft.com>, Isaac Corley <isaac.corley@my.utsa.edu>, Nils Lehmann <n.lehmann@tum.de>, Ashwin Nair <ashnair0007@gmail.com>
License-Expression: MIT
Project-URL: Codecov, https://app.codecov.io/gh/torchgeo/torchgeo
Project-URL: Documentation, https://torchgeo.readthedocs.io
Project-URL: Homepage, https://github.com/torchgeo/torchgeo
Project-URL: Slack, https://torchgeo.slack.com
Keywords: pytorch,deep learning,machine learning,remote sensing,satellite imagery,earth observation,geospatial
Classifier: Development Status :: 4 - Beta
Classifier: Intended Audience :: Science/Research
Classifier: Operating System :: OS Independent
Classifier: Programming Language :: Python :: 3
Classifier: Programming Language :: Python :: 3.11
Classifier: Programming Language :: Python :: 3.12
Classifier: Programming Language :: Python :: 3.13
Classifier: Programming Language :: Python :: 3.14
Classifier: Topic :: Scientific/Engineering :: Artificial Intelligence
Classifier: Topic :: Scientific/Engineering :: GIS
Requires-Python: >=3.11
License-File: LICENSE
Requires-Dist: einops>=0.3
Requires-Dist: geopandas>=0.12.1
Requires-Dist: jsonargparse[signatures]>=4.25
Requires-Dist: kornia>=0.8.2
Requires-Dist: lightly!=1.4.26,>=1.4.5
Requires-Dist: lightning!=2.3.*,!=2.5.0,!=2.5.5,!=2.5.6,>=2
Requires-Dist: matplotlib>=3.6
Requires-Dist: numpy>=1.24
Requires-Dist: pandas>=1.5
Requires-Dist: pillow>=9.2
Requires-Dist: pyproj>=3.4
Requires-Dist: rasterio>=1.4.3
Requires-Dist: segmentation-models-pytorch>=0.5
Requires-Dist: shapely>=2
Requires-Dist: timm>=1.0.3
Requires-Dist: torch>=2
Requires-Dist: torchmetrics>=1.2
Requires-Dist: torchvision>=0.15.1
Requires-Dist: typing-extensions>=4.5
Provides-Extra: datasets
Requires-Dist: h5py>=3.8; extra == "datasets"
Requires-Dist: laspy>=2.5.3; extra == "datasets"
Requires-Dist: netcdf4>=1.6.1; extra == "datasets"
Requires-Dist: pandas[parquet]>=2; extra == "datasets"
Requires-Dist: pycocotools>=2.0.7; extra == "datasets"
Requires-Dist: requests>=2.23.0; extra == "datasets"
Requires-Dist: rioxarray>=0.14.1; extra == "datasets"
Requires-Dist: scikit-image>=0.20; extra == "datasets"
Requires-Dist: scipy>=1.9.2; extra == "datasets"
Requires-Dist: webdataset>=0.2.4; extra == "datasets"
Requires-Dist: xarray>=0.17; extra == "datasets"
Provides-Extra: docs
Requires-Dist: ipywidgets>=7; extra == "docs"
Requires-Dist: myst-parser>=0.18.0; extra == "docs"
Requires-Dist: nbsphinx>=0.8.5; extra == "docs"
Requires-Dist: pydata-sphinx-theme>=0.14.0; extra == "docs"
Requires-Dist: sphinx>=5.3; extra == "docs"
Provides-Extra: models
Requires-Dist: microsoft-aurora>=1.6; extra == "models"
Provides-Extra: style
Requires-Dist: mypy>=1.16; extra == "style"
Requires-Dist: pandas-stubs>=1.5; extra == "style"
Requires-Dist: ruff>=0.9; extra == "style"
Requires-Dist: types-requests>=2.23; extra == "style"
Requires-Dist: types-shapely>=2; extra == "style"
Provides-Extra: tests
Requires-Dist: nbmake>=1.3.3; extra == "tests"
Requires-Dist: packaging>=20.9; extra == "tests"
Requires-Dist: pytest>=7.3; extra == "tests"
Requires-Dist: pytest-cov>=4; extra == "tests"
Provides-Extra: all
Requires-Dist: torchgeo[datasets,docs,models,style,tests]; extra == "all"
Dynamic: license-file
